vcf_converter/__init__.py
vcf_converter/cnv_vcf2json.py
cnv_vcf2json-2.0.0.dist-info/METADATA
cnv_vcf2json-2.0.0.dist-info/WHEEL
cnv_vcf2json-2.0.0.dist-info/entry_points.txt
cnv_vcf2json-2.0.0.dist-info/top_level.txt
cnv_vcf2json-2.0.0.dist-info/RECORD
