Metadata-Version: 2.1
Name: cnv_vcf2json
Version: 2.0.0
Summary: Converts the CNVkit structural variants VCF file into JSON format
Author: Khaled Jumah
Author-email: khalled.jooma@yahoo.com
License: CC-BY-NC-4.0
Requires-Dist: jsonschema
